pfm_app/__init__.py
pfm_app/__main__.py
pfm_app/currency.py
pfm_app/portfolio.py
pfm_app/securities.py
tests/tests_securities.py
pfm_app-0.1.0.dist-info/METADATA
pfm_app-0.1.0.dist-info/WHEEL
pfm_app-0.1.0.dist-info/entry_points.txt
pfm_app-0.1.0.dist-info/top_level.txt
pfm_app-0.1.0.dist-info/RECORD
